subtree_metric/__init__.py
subtree_metric/classifier_utils.py
subtree_metric/stm.py
subtree_metric/tree_constructor.py
subtree_metric-0.2.4.dist-info/METADATA
subtree_metric-0.2.4.dist-info/WHEEL
subtree_metric-0.2.4.dist-info/top_level.txt
subtree_metric-0.2.4.dist-info/RECORD
