Metadata-Version: 2.1
Name: subtree-metric
Version: 0.2.4
Summary: Subtree Metric for the translation evaluation
Home-page: https://github.com/WhiteJaeger/nlp-metrics
Author: Kashchikhin Andrej
Author-email: logerk3@gmail.com
License: UNKNOWN
Project-URL: Bug Tracker, https://github.com/WhiteJaeger/nlp-metrics/issues
Project-URL: Web Application, https://nlp-metrics.herokuapp.com
Platform: UNKNOWN
Classifier: Programming Language :: Python :: 3
Classifier: License :: OSI Approved :: MIT License
Classifier: Operating System :: OS Independent
Requires-Python: >=3.6
Requires-Dist: nltk (==3.6.2)
Requires-Dist: spacy (==3.0.5)
Requires-Dist: sklearn (==0.0)
Requires-Dist: scikit-learn (==0.24.2)
